LICENSE
MANIFEST.in
README.rst
bottle_swagger.py
requirements.txt
setup.cfg
setup.py
bottle_swagger.egg-info/PKG-INFO
bottle_swagger.egg-info/SOURCES.txt
bottle_swagger.egg-info/dependency_links.txt
bottle_swagger.egg-info/requires.txt
bottle_swagger.egg-info/top_level.txt
test/test_bottle_swagger.py