Metadata-Version: 1.1
Name: bottle-swagger
Version: 1.0.3
Summary: Swagger integration for Bottle
Home-page: https://github.com/ampedandwired/bottle-swagger
Author: Charles Blaxland
Author-email: charles.blaxland@gmail.com
License: MIT
Download-URL: https://github.com/ampedandwired/bottle-swagger/archive/v1.0.3.tar.gz
Platform: any
Classifier: Environment :: Web Environment
Classifier: Environment :: Plugins
Classifier: Framework :: Bottle
Classifier: Intended Audience :: Developers
Classifier: License :: OSI Approved :: MIT License
Classifier: Operating System :: OS Independent
Classifier: Programming Language :: Python
Classifier: Topic :: Internet :: WWW/HTTP :: Dynamic Content
Classifier: Topic :: Software Development :: Libraries :: Python Modules
